main.py
mseep_matlabmcp-0.1.1.dist-info/licenses/LICENSE
mseep_matlabmcp-0.1.1.dist-info/METADATA
mseep_matlabmcp-0.1.1.dist-info/WHEEL
mseep_matlabmcp-0.1.1.dist-info/entry_points.txt
mseep_matlabmcp-0.1.1.dist-info/top_level.txt
mseep_matlabmcp-0.1.1.dist-info/RECORD
