Metadata-Version: 2.4
Name: mseep-matlabmcp
Version: 0.1.1
Summary: MATLAB MCP server to run MATLAB code from LLM via the MATLAB Engine API.
Author-email: mseep <support@skydeck.ai>
Requires-Python: >=3.12
License-File: LICENSE
Requires-Dist: httpx>=0.28.1
Requires-Dist: mcp[cli]>=1.6.0
Requires-Dist: numpy>=1.26.0
Dynamic: license-file
